<?xml version="1.0" encoding="UTF-8"?>
<objects serializationModel="Studio.02.03.00">
	<object class="AudioFile" id="{99f9e459-c50e-4389-838f-060f711309fc}">
		<property name="assetPath">
			<value>Weapons/Explosion/weapons_explosion_large.ogg</value>
		</property>
		<property name="frequencyInKHz">
			<value>44.0999985</value>
		</property>
		<property name="channelCount">
			<value>2</value>
		</property>
		<property name="length">
			<value>1.7233333333333334</value>
		</property>
		<relationship name="masterAssetFolder">
			<destination>{bf682a93-1b20-43b8-a79d-e22c2d47d689}</destination>
		</relationship>
	</object>
</objects>
